odoo/addons/pms_account_move_budget/README.rst
odoo/addons/pms_account_move_budget/__init__.py
odoo/addons/pms_account_move_budget/__manifest__.py
odoo/addons/pms_account_move_budget/i18n/it.po
odoo/addons/pms_account_move_budget/i18n/pms_account_move_budget.pot
odoo/addons/pms_account_move_budget/models/__init__.py
odoo/addons/pms_account_move_budget/models/account_move_budget_line.py
odoo/addons/pms_account_move_budget/readme/DESCRIPTION.rst
odoo/addons/pms_account_move_budget/static/description/icon.png
odoo/addons/pms_account_move_budget/static/description/index.html
odoo/addons/pms_account_move_budget/views/account_move_budget_line_view.xml
odoo14_addon_pms_account_move_budget-14.0.1.0.1.dev5.dist-info/METADATA
odoo14_addon_pms_account_move_budget-14.0.1.0.1.dev5.dist-info/WHEEL
odoo14_addon_pms_account_move_budget-14.0.1.0.1.dev5.dist-info/top_level.txt
odoo14_addon_pms_account_move_budget-14.0.1.0.1.dev5.dist-info/RECORD
