Metadata-Version: 2.1
Name: odoo14-addon-pms_account_move_budget
Version: 14.0.1.0.1.dev5
Summary: Add Property Field in Account Move Budget
Home-page: https://github.com/OCA/pms
Author: Comunitea, Odoo Community Association (OCA)
Author-email: support@odoo-community.org
License: AGPL-3
Classifier: Programming Language :: Python
Classifier: Framework :: Odoo
Classifier: Framework :: Odoo :: 14.0
Classifier: License :: OSI Approved :: GNU Affero General Public License v3
Requires-Python: >=3.6
Requires-Dist: odoo14-addon-account-move-budget
Requires-Dist: odoo<14.1dev,>=14.0a
